mem.v
/* instruction memory */

`timescale 1ps/1ps

module mem(input clk,
    // read ports
    input [7:0]raddr0, output [7:0]rdata0,
    // write port
    input writeEnable, input [7:0]writeAddress, input [7:0]writeData);

    reg [7:0]mem[1023:0];

    /* Simulation -- read initial content from file */
    initial begin
        $readmemh("mem.hex",mem);
    end

    /* memory address register */
    reg [7:0]in0 = 16'hxxxx;
    reg [7:0]in1 = 16'hxxxx;

    /* memory data register */
    reg [7:0]out0 = 16'hxxxx;
    reg [7:0]out1 = 16'hxxxx;

    assign rdata0 = out0;
    assign rdata1 = out1;

    always @(posedge clk) begin
        if (writeEnable) begin
            $display("#mem[%x] <= %x",writeAddress,writeData);
            mem[writeAddress] <= writeData;
        end
        in0 <= raddr0;
        out0 <= mem[in0];        
    end

endmodule

alu.v
`timescale 1ps/1ps

// original has AND OR XOR ADD SHIFTRIGHT //
// but I have no idea how these create other operations so just hardcoding them //

// OPS // 
`define ADD 0
`define SUB 1
`define AND 2
`define OR  3
`define XOR 4
`define INC 5
`define DEC 6
`define SHR 7
`define SHL 8
`define RTR 9
`define RTL 10
`define LD  12  // not planning on putting lds through the adder 


module alu (input clk,
            input [7:0]operand1,
            input [7:0]operand2,
            input carry,
            input [4:0]op,
            output [7:0]result,
            output carrybit,
            output overflow
           );

    reg [7:0]output_reg = 8'hxx;
    reg carry_reg = 1'hx;
    reg overflow_reg = 1'hx;

    wire [7:0]operation_result = op == `ADD ? operand1 + operand2 + carry:
                                 op == `SUB ? operand1 - operand2 - carry:
                                 op == `AND ? operand1 & operand2 :
                                 op == `OR  ? operand1 | operand2 :
                                 op == `XOR ? operand1 ^ operand2 :
                                 op == `INC ? operand1 + 1        :
                                 op == `DEC ? operand1 - 1        :
                                 op == `SHR ? operand1 >> 1       :
                                 op == `SHL ? operand1 << 1       :
                                 op == `RTR ?(operand1 >> 1) & (carry << 7 | 8'h7F) :
                                 op == `RTL ?(operand1 << 1) | carry                :
                                 op == `LD  ? operand1            : // no operation needed
                                 8'hxx;
    
    wire carry_wire = (op == `ADD) ? 
                    ((operand1[7] == 1) && (operand2[7] == 1)) ||
                    ((operand1[7] != operand2[7]) && (newvalue[7] == 0)): 
                    (op == `SUB) ? (newvalue <= 0) : 0; // FIX THIS 

    wire overflow_wire = i_adc && immediate ? 
                    ((registers[0][7] == 1) && (operand[7] == 1) && (newvalue[7] != 1) ||
                     (registers[0][7] == 0) && (operand[7] == 0) && (newvalue[7] != 0)) : 0; 

    assign result = output_reg;
    assign carrybit = carry_reg;
    assign overflow = overflow_reg;

    // ALU operations take 1 cycle 
    always @(posedge clk)begin
        output_reg <= operation_result;
        carry_reg <= carry_wire;
        overflow_reg <= overflow_wire;
    end
endmodule

cpu.v
`timescale 1ps/1ps

// STATES //
`define INIT 10
`define F0 0
`define F1 1 
`define HLT 2
`define F2 3
`define HLT2 4
`define M0 5
`define WB 6
`define X0 7

// STATUS REGISTER BITS//
`define NEGATIVE 7
`define OVERFLOW 6  // 5 is unused
`define BREAK    4
`define DECIMAL  3
`define INT      2
`define ZERO     1
`define CARRY    0

// HEX //
`define A 10
`define B 11
`define C 12
`define D 13
`define E 14
`define F 15

// REGISTERS //
`define AC 0
`define X 1
`define Y 2
`define SP 3

// OPS // 
`define ADD 0
`define SUB 1
`define AND 2
`define OR  3
`define XOR 4
`define INC 5
`define DEC 6
`define SHR 7
`define SHL 8
`define RTR 9
`define RTL 10
`define LD  12

// RAM access time ~70ns?
// NES version of 6502 doesn't use BCD 

module cpu(input clk);

    // set to 1 for print statments
    reg verbose = 0;
    reg status_v = 0;
    reg [15:0] cycles = 0;

    // inst decoding // 
    wire isOdd = inst[7:4] % 2 == 1;
    wire isEven = inst[7:4] % 2 == 0;
    wire higher_half = inst[7:4] >= 8;
    
    // inst groups 
    wire oddops = low(inst, 1) || low(inst, 5) ||
                  low(inst, 9) || low(inst, `D);
    wire evenops = low(inst, 6) || (low(inst, 10) && !higher_half) || 
                   low(inst, 14);
    wire zerofourc = low(inst, 0) || low(inst, 4) ||
                     low(inst, `C);

    // insts are split into high and low nibbles
    function high;
    input [7:0] inst;
    input [3:0] code;
    high = inst[7:4] == code;
    endfunction

    function low;
    input [7:0] inst;
    input [3:0] code;
    low = inst[3:0] == code;
    endfunction

    // 0 low-nibble (!higher_half) 
    wire i_brk = inst == 0;
    wire i_jsr = inst == 8'h20;
    wire i_rti = inst == 8'h40;
    wire i_rts = inst == 8'h60;
   
    // branches 0 low-nibble (odd high-nibble)
    wire branch = ((inst[3:0] == 0) && isOdd) || i_jmp;
    wire i_bpl = branch && high(inst, 1);
    wire i_bmi = branch && high(inst, 3);
    wire i_bvc = branch && high(inst, 5);
    wire i_bvs = branch && high(inst, 7);
    wire i_bcc = branch && high(inst, 9);
    wire i_bcs = branch && high(inst, `B);
    wire i_bne = branch && high(inst, `D);
    wire i_beq = branch && high(inst, `F);
    wire i_bit = (inst == 8'h24) || (inst == 8'h2c);
    wire i_jmp = (inst == 8'h4c) || (inst == 8'h6c);

    // 0, 4, c low-nibble (zerofourc)
    wire i_cpx = zerofourc && high(inst, `E);
    wire i_cpy = zerofourc && high(inst, `C);
    wire i_ldy = zerofourc && !(inst == 8'hb0) && (high(inst, 10) || high(inst, 11));
    
    // 1, 5, 9, D low-nibble (oddops)
    wire i_ora = oddops && (high(inst, 0) || high(inst, 1));
    wire i_and = oddops && (high(inst, 2) || high(inst, 3));
    wire i_eor = oddops && (high(inst, 4) || high(inst, 5));
    wire i_adc = oddops && (high(inst, 6) || high(inst, 7));
    wire i_sta = oddops && (high(inst, 8) || high(inst, 9));
    wire i_lda = (oddops && (high(inst, `A) || high(inst, `B))) || (inst == 8'ha2);
    wire i_cmp = oddops && (high(inst, `C) || high(inst, `D));
    wire i_sbc = oddops && (high(inst, `E) || high(inst, `F));

    // 6, 10 (lower half high), 14 low-nibble (evenops)
    wire i_asl = evenops && (high(inst, 0) || high(inst, 1));
    wire i_rol = evenops && (high(inst, 2) || high(inst, 3));
    wire i_lsr = evenops && (high(inst, 4) || high(inst, 5));
    wire i_ror = evenops && (high(inst, 6) || high(inst, 7));
    wire i_stx = evenops && (high(inst, 8) || high(inst, 9));
    wire i_ldx = evenops && (high(inst, `A) || high(inst, `B));
    wire i_dec = evenops && (high(inst, `C) || high(inst, `D));
    wire i_inc = evenops && (high(inst, `E) || high(inst, `F));

    // flags 8 low-nibble & odd high-nibble (tya exception)
    wire flags = isOdd && low(inst, 8) && !i_tya;
    wire i_clc = flags && high(inst, 1);
    wire i_sec = flags && high(inst, 3);
    wire i_cli = flags && high(inst, 5);
    wire i_sei = flags && high(inst, 7);
    wire i_clv = flags && high(inst, 11);
    wire i_cld = flags && high(inst, 13);
    wire i_sed = flags && high(inst, 15);

    // stack 8 low-nibble & even high-nibble & !higher_half
    wire stack_inst = isEven && !higher_half && (inst[3:0] == 8);
    wire i_php = stack_inst && (inst[7:4] == 0);
    wire i_plp = stack_inst && (inst[7:4] == 2);
    wire i_pha = stack_inst && (inst[7:4] == 4);
    wire i_pla = stack_inst && (inst[7:4] == 6);

    // transfer (no pattern...?)
    wire i_tax = inst == 8'haa; 
    wire i_tay = inst == 8'ha8;
    wire i_tsx = inst == 8'hba;
    wire i_txa = inst == 8'h8a;
    wire i_txs = inst == 8'h9a;
    wire i_tya = inst == 8'h98; 

    // misc 
    wire i_sty = (inst == 8'h84) || (inst == 8'h94) || (inst == 8'h8c);
    wire i_nop = (inst == 8'hea);
    wire i_dex = inst == 8'hca;
    wire i_dey = inst == 8'h88;
    wire i_inx = inst == 8'he8;
    wire i_iny = inst == 8'hc8;

    // modes
    wire immediate = (inst == 8'ha2) || (low(inst, 9) && isEven) || (low(inst, 0) && higher_half && isEven);            // 1 operand
    wire absolute  = ((low(inst, `C) || low(inst, `D) || low(inst, `E)) && isEven) || (inst == 8'h20) && !indirect;     // 2 operands
    wire zpg_absolute = (low(inst, 4) || low(inst, 5) || low(inst, 6)) && isEven;                                       // 1 operand
    wire implied = (inst == 8'h40) || (inst == 8'h60) || (inst == 0) || low(inst, 8) || (low(inst, `A) && higher_half); // 0 operands
    wire accumulator = low(inst, `A) && !higher_half && isEven;                                                         // 0 operands
    wire abs_indexed_x = (low(inst, `C) || low(inst, `D) || low(inst, `E)) && isOdd && !abs_indexed_y;                  // 2 operands
    wire abs_indexed_y = (inst == 8'hbe) || (low(inst, 9) && isOdd);                                                    // 2 operands
    wire zpg_indexed_x = (low(inst, 4) || low(inst, 5) || low(inst, 6)) && isOdd && !zpg_indexed_y;                     // 1 operand
    wire zpg_indexed_y = (low(inst, 6) && (high(inst, 9) || high(inst, `B)));                                           // 1 operand
    wire indirect = inst == 8'h6c;                                                                                      // 2 operands
    wire indirect_x = low(inst, 1) && isEven;                                                                           // 1 operand
    wire indirect_y = low(inst, 1) && isOdd;                                                                            // 1 operand
    wire relative = low(inst, 0) && isOdd;                                                                              // 1 operand

    // ------------- REGISTERS -------------- //
    reg [7:0] registers[3:0];
    reg [15:0]pc = 0;
    reg [7:0] sr = 8'b00110000;
    // -------------------------------------- //
    
    wire modify_ac = i_lda | i_adc | i_and | i_asl | i_eor | i_lsr | 
                     i_ora | i_rol | i_ror | i_sbc | i_txa | i_tya;
    wire modify_x  = i_tax | i_inx | i_tsx | i_dex | i_ldx;
    wire modify_y  = i_dey | i_iny | i_ldy | i_tay;
    wire modify_sp = i_txs;

    wire [1:0]modified_reg = modify_ac ? `AC :
                             modify_x  ? `X  :
                             modify_y  ? `Y  :
                             modify_sp ? `SP :
                             2'bxx;       

    wire register_ren = state == `F0; 
    wire ready = (modify_ac | modify_x | modify_y | modify_sp) & register_ren;
    wire [7:0] newvalue = alu_result;

    //----------- REGSITER UPDATE -----------------//
    always @(posedge clk) begin
        // only change one register at a time 
        if (ready) begin
            if (alu_carry)begin
                if (verbose)
                    $display("carrying!");
                sr[`CARRY] <= 1;
            end
            if (alu_overflow)begin
                if (verbose)
                    $display("overflowed!");
                sr[`OVERFLOW] <= 1;
            end
            if (newvalue[7] == 1)
                sr[`NEGATIVE] <= 1;
            else
                sr[`NEGATIVE] <= 0;
            if (newvalue == 0)
                sr[`ZERO] <= 1;
            else 
                sr[`ZERO] <= 0;
            if (i_rol | i_asl) begin
                sr[`CARRY] <= operand1[7];
            end
            if (i_ror | i_lsr)begin
                sr[`CARRY] <= operand1[0];
             end
            
            registers[modified_reg] <= newvalue;
            $display("#regs[%d] <= %x", modified_reg, newvalue);
        end
    end
    // ------------------------------------------- //

    // ------------- ALU --------------- //

    wire [4:0] op = i_adc ? `ADD :
                    i_sbc ? `SUB : 
                    i_and ? `AND :
                    i_ora ? `OR  : 
                    i_eor ? `XOR : 
                    (i_inx | i_iny | i_inc) ? `INC :
                    (i_dex | i_dey | i_dec) ? `DEC :
                    i_lsr ? `SHR :
                    i_asl ? `SHL :
                    i_ror ? `RTR :
                    i_rol ? `RTL :
                    (i_lda | i_ldx | i_ldy | i_tax | 
                    i_tay | i_tsx | i_txa | i_txs | 
                    i_tya) ? `LD : 4'bx;

    wire [7:0] operand1 = (state == `M0) && (i_inc | i_dec | i_asl | i_lsr | i_rol | i_ror) ? memOut :
                          i_adc | i_sbc | i_and | i_ora | i_eor | 
                        ((i_lsr | i_asl | i_ror | i_rol) & accumulator) 
                        | i_tax | i_tay ? registers[`AC] : 
                          i_inx | i_dex | i_txa | i_txs ? registers[`X] : 
                          i_iny | i_dey | i_tya ? registers[`Y] : 
                          i_tsx ? registers[`SP] : 
                          (i_lda | i_ldx | i_ldy) ? memOut : 8'hxx;

    wire [7:0] operand2 = i_adc | i_sbc | i_and | i_ora | i_eor ? memOut : 8'hxx;
                          
    wire [7:0] alu_result;
    wire alu_carry;
    wire alu_overflow;

    alu a0(clk, operand1, operand2, sr[`CARRY], op, alu_result, alu_carry, alu_overflow);
    // --------------------------------- //


    // --------------------------- MEMORY --------------------------- // 
    reg [7:0] temp_low = 8'hx;
    wire [7:0]memOut;
    wire [15:0]memIn = absolute & reading & (state == `F2) ? {memOut, temp_low} :
                       zpg_absolute & reading & (state == `F1) ? {8'h00, memOut} : 
                      {8'h00, pc}; 

    wire wen = zpg_absolute && !reading ? (state == `F1) : 
               writeback ? (state == `M0) : write_enable;

    wire [15:0] write_address = absolute ? {memOut , temp_low} : 
                                zpg_absolute & !writeback ? {8'h00, memOut} : 
                                writeback & (state == `M0) ? addresscache : waddr;
    wire [7:0] reswire = zpg_absolute & !writeback ? write_value : 
                         writeback & (state == `M0) ? writeback_value : res;

    reg write_enable = 1'bx;
    reg [7:0]res = 8'bxx;
    reg [15:0]waddr = 8'bxx;

    mem i0(clk,memIn,memOut, write_enable, waddr, res);

    // --------------------------------------------------------------- //

    reg [15:0] state = `INIT;
    reg [7:0]inst = 8'hxx;
    reg [15:0] addresscache;

    wire reading = (absolute | zpg_absolute) && !i_sta && !i_stx && !i_sty;
    wire writeback = i_asl | i_dec | i_inc | i_lsr | i_rol | i_ror;

    wire [7:0] writeback_value = i_asl ? (memOut << 1 ) :
                                 i_dec ? (memOut - 1 )  : 
                                 i_inc ? (memOut + 1 )  :
                                 i_lsr ? (memOut >> 1 ) :
                                 i_rol ? (memOut << 1) | (carry) : 
                                 i_ror ? (memOut >> 1) & (carry << 7 | 8'h7F) : 8'hxx;
    // status bits
    wire negative  = sr[7];
    wire overflow  = sr[6];
    wire ignored   = sr[5];
    wire break     = sr[4];
    wire decimal   = sr[3];
    wire interrupt = sr[2];
    wire zero      = sr[1];
    wire carry     = sr[0];

    wire [7:0]operand = memOut;
    
    wire crossed = 0; // if a page boundary is crossed

    wire [7:0] write_value = i_sta ? registers[`AC] :
                             i_stx ? registers[`X]  :
                             i_sty ? registers[`Y]  : 
                             i_asl ? 0              :
                             i_dec ? 0              :
                             i_inc ? 0              :
                             i_lsr ? 0              :
                             i_rol ? 0              :
                             i_ror ? 0              :
                             8'hxx;

    // for debugging 
    //modePrinter mp(clk, immediate, absolute, zpg_absolute, implied, accumulator, abs_indexed_x, abs_indexed_y, zpg_indexed_x, zpg_indexed_y, indirect, indirect_x, indirect_y, relative, inst, newinst);

    //instprinter ip(clk, i_adc, i_and, i_asl, i_bcc, i_bcs, i_beq, i_bit, i_bmi, i_bne, i_bpl, i_brk, i_bvc, i_bvs, i_clc, i_cld, i_cli, i_clv, i_cmp, i_cpx, i_cpy, i_dec, i_dex, i_dey, i_eor, i_inc, i_inx, i_iny, i_jmp, i_jsr, i_lda, i_ldx, i_ldy, i_lsr, i_nop, i_ora, i_pha, i_php, i_pla, i_plp, i_rol, i_ror, i_rti, i_rts, i_sbc, i_sec, i_sed, i_sei, i_sta, i_stx, i_sty, i_tax, i_tay, i_tsx, i_txa, i_txs, i_tya, inst);
    // implied = 1 byte
    // absolute, absolute x, absolute y = 3 bytes 
    // else 2 bytes
    always @(posedge clk) begin
        case (state)
            `INIT: begin
                pc <= pc + 1;
                registers[0] = 0;
                registers[1] = 0;
                registers[2] = 0;
                registers[3] = 0;
                state <= `F0;
            end
            `F0: begin 
                // ----- fetch opcode + finish last instruction ----- // 
                write_enable <= 0;
                if (verbose)
                    $display("F0 %x %x", memOut, inst);
                if (memOut === 8'hxx)
                    state <= `HLT;
                else 
                    state <= `F1;
                
                if (!(inst === 8'hxx) & (accumulator | implied)) begin
                    inst <= addresscache;
                    pc <= pc + 1;
                end
                else begin
                    pc <= pc + 1;
                    inst <= memOut;
                end

            end
            `F1 : begin
                // ----------------- decode --------------------- //
                if (verbose)
                    $display("F1 %x %x", memOut, inst);
                if (memOut === 8'hxx | i_brk)
                    state <= `HLT;
                if (status_v)
                    $display("sr %b", sr);

                if (accumulator | implied) begin
                    // memOut is discarded & re-read
                    //inst <= memOut;
                    addresscache <= memOut;
                    state <= `F0;
                    //pc <= pc + 1;
                end
                else if (immediate) begin
                    // memOut is only operand - no further reads needed 
                    state <= `F0;
                    pc = pc + 1;
                end
                if (absolute) begin
                    pc <= pc + 1;
                    temp_low <= memOut; 
                    state <= `F2;
                end
                if (zpg_absolute)begin 
                    addresscache <= memIn;
                    if (!reading) begin
                        state <= `WB;
                        write_enable <= 1;
                        waddr <= {8'h00, memOut};
                        res <= write_value;
                    end 
                    else
                        state <= `M0;
                end
                //if (implied | accumulator)begin
                //    inst <= memOut;         // decoding completed!
                //end
            end
            `F2 : begin
                // ------------- reading second operand ------------ //
               if (verbose)
                    $display("F2 %x %x", memOut, inst);
                    
                if (!reading) begin// lda, ldx, ldy done after this step
                    write_enable <= 1;
                    waddr <= {memOut, temp_low};
                    res <= write_value;
                    state <= `WB;
                    //pc <= pc + 1;
                end
                else begin
                    addresscache <= {memOut, temp_low}; 
                    state <= `M0;
                end
            end
            `M0 : begin
                // -------------- reading a value from memory ------------ // 
                if (verbose)
                    $display("M0 %x %x", memOut, inst);
                if (!reading)begin
                    state <= `WB;
                end
                if (writeback)begin // may have to move this
                    state <= `X0;
                end
                else begin 
                    pc <= pc + 1;
                    state <= `F0;
                end
            end
          `X0 : begin
                // --------------- using the ALU for writeback --------------- //
                 if (verbose)
                    $display("WB %x %x", memOut, inst);
                 state <= `WB;
                 res <= alu_result;
                 write_enable <= 1;
                 waddr <= addresscache;
 
                // ------ update status register ----- // 
                if (writeback & i_rol)
                    sr[`CARRY] <= alu_result[7];
                if (writeback & i_ror)
                    sr[`CARRY] <= alu_result[0];
                if (writeback & alu_result == 0)
                    sr[`ZERO] <= 1;
                else 
                    sr[`ZERO] <= 0;
                if (writeback & alu_result[7] == 1)
                    sr[`NEGATIVE] <= 1;
                else
                    sr[`NEGATIVE] <= 0;
           end
          `WB : begin
                // -------------- write back to memory ------------------- //
                write_enable <= 0;
                if (verbose)
                    $display("WB %x %x", memOut, inst);
                               pc <= pc + 1;
                state <= `F0;
           end 
            `HLT : begin
                if (verbose)
                    $display("HLT %x %x", memOut, inst);
                state <= `HLT2;
            end
            `HLT2 : begin
                $finish;
            end
        endcase
        
        cycles <= cycles + 1;
    end

endmodule

clock_gen.v
/* clock */
`timescale 1ps/1ps


// NOTE: subject to change - how to synchronize PPU/CPU? 
// PPU = m_clock / 4  = 21.4773 MHz / 4  = 5.37 MHz
// CPU = m_clock / 12 = 21.4773 MHz / 12 = 1.79 MHz

module clock_gen (input m_clk, output ppu_clk, output cpu_clk);
    
    reg [3:0] cycle = 0;
    reg ppu = 1;
    reg cpu = 0;

    assign ppu_clk = ppu;
    assign cpu_clk = cpu;

    // cpu only runs 1/12 during the 12th cycle (cycle 11) 
    // ppu only runs 4/12 during cycles 0, 3, 6, 9
    always @(posedge m_clk) begin
        if (cycle == 10)begin
            cpu <= 1;
            ppu <= 0;
        end
        else if (cycle == 11 || cycle == 2 || cycle == 5 || cycle == 8) begin
            ppu <= 1;
            cpu <= 0;
        end
        else begin
            ppu <= 0;
            cpu <= 0;
        end
            
        if (cycle == 11)
            cycle <= 0;
        else
            cycle <= cycle + 1;
    end
endmodule

master_clock.v
/* clock */
`timescale 1ps/1ps

// 21.4773 MHz = 21477300 cycles / second
// 21477300 cycles / second = 1 cycle = 46.56 ns per cycle ( round ?? ) 
// 46.56 ns = 46560.7874 ps

module master_clock(output clk);
    reg theClock = 1;

    assign clk = theClock;
    
    always begin
        #46560;
        theClock = !theClock;
    end
endmodule

nes.v
`timescale 1ps/1ps


module main();


wire m_clk;
// Master clock is split into PPU clock and CPU clock 
master_clock c0(m_clk);

    initial begin
        $dumpfile("cpu.vcd");
        $dumpvars(1,main);
        $dumpvars(1,c);
    end

wire ppu_clk;
wire cpu_clk;
clock_gen c1(m_clk, ppu_clk, cpu_clk);

wire [15:0]address_bus_in;
wire [7:0] data_bus_in;
wire [15:0]address_bus_out;
wire [7:0] data_bus_out;
wire wen;

cpu c(cpu_clk);

endmodule

cpu.vcd
$date
	Tue May 12 16:43:51 2015
$end
$version
	Icarus Verilog
$end
$timescale
	1ps
$end
$scope module main $end
$var wire 1 ! cpu_clk $end
$var wire 1 " m_clk $end
$var wire 1 # ppu_clk $end
$upscope $end
$scope module main $end
$scope module c $end
$var wire 1 $ abs_indexed_x $end
$var wire 1 % abs_indexed_y $end
$var wire 1 & absolute $end
$var wire 1 ' accumulator $end
$var wire 1 ( alu_carry $end
$var wire 1 ) alu_overflow $end
$var wire 8 * alu_result [7:0] $end
$var wire 1 + branch $end
$var wire 1 , break $end
$var wire 1 - carry $end
$var wire 1 ! clk $end
$var wire 1 . crossed $end
$var wire 1 / decimal $end
$var wire 1 0 evenops $end
$var wire 1 1 flags $end
$var wire 1 2 higher_half $end
$var wire 1 3 i_adc $end
$var wire 1 4 i_and $end
$var wire 1 5 i_asl $end
$var wire 1 6 i_bcc $end
$var wire 1 7 i_bcs $end
$var wire 1 8 i_beq $end
$var wire 1 9 i_bit $end
$var wire 1 : i_bmi $end
$var wire 1 ; i_bne $end
$var wire 1 < i_bpl $end
$var wire 1 = i_brk $end
$var wire 1 > i_bvc $end
$var wire 1 ? i_bvs $end
$var wire 1 @ i_clc $end
$var wire 1 A i_cld $end
$var wire 1 B i_cli $end
$var wire 1 C i_clv $end
$var wire 1 D i_cmp $end
$var wire 1 E i_cpx $end
$var wire 1 F i_cpy $end
$var wire 1 G i_dec $end
$var wire 1 H i_dex $end
$var wire 1 I i_dey $end
$var wire 1 J i_eor $end
$var wire 1 K i_inc $end
$var wire 1 L i_inx $end
$var wire 1 M i_iny $end
$var wire 1 N i_jmp $end
$var wire 1 O i_jsr $end
$var wire 1 P i_lda $end
$var wire 1 Q i_ldx $end
$var wire 1 R i_ldy $end
$var wire 1 S i_lsr $end
$var wire 1 T i_nop $end
$var wire 1 U i_ora $end
$var wire 1 V i_pha $end
$var wire 1 W i_php $end
$var wire 1 X i_pla $end
$var wire 1 Y i_plp $end
$var wire 1 Z i_rol $end
$var wire 1 [ i_ror $end
$var wire 1 \ i_rti $end
$var wire 1 ] i_rts $end
$var wire 1 ^ i_sbc $end
$var wire 1 _ i_sec $end
$var wire 1 ` i_sed $end
$var wire 1 a i_sei $end
$var wire 1 b i_sta $end
$var wire 1 c i_stx $end
$var wire 1 d i_sty $end
$var wire 1 e i_tax $end
$var wire 1 f i_tay $end
$var wire 1 g i_tsx $end
$var wire 1 h i_txa $end
$var wire 1 i i_txs $end
$var wire 1 j i_tya $end
$var wire 1 k ignored $end
$var wire 1 l immediate $end
$var wire 1 m implied $end
$var wire 1 n indirect $end
$var wire 1 o indirect_x $end
$var wire 1 p indirect_y $end
$var wire 1 q interrupt $end
$var wire 1 r isEven $end
$var wire 1 s isOdd $end
$var wire 16 t memIn [15:0] $end
$var wire 8 u memOut [7:0] $end
$var wire 2 v modified_reg [1:0] $end
$var wire 1 w modify_ac $end
$var wire 1 x modify_sp $end
$var wire 1 y modify_x $end
$var wire 1 z modify_y $end
$var wire 1 { negative $end
$var wire 8 | newvalue [7:0] $end
$var wire 1 } oddops $end
$var wire 5 ~ op [4:0] $end
$var wire 8 !" operand [7:0] $end
$var wire 8 "" operand1 [7:0] $end
$var wire 8 #" operand2 [7:0] $end
$var wire 1 $" overflow $end
$var wire 1 %" reading $end
$var wire 1 &" ready $end
$var wire 1 '" register_ren $end
$var wire 1 (" relative $end
$var wire 8 )" reswire [7:0] $end
$var wire 1 *" stack_inst $end
$var wire 1 +" wen $end
$var wire 16 ," write_address [15:0] $end
$var wire 8 -" write_value [7:0] $end
$var wire 1 ." writeback $end
$var wire 8 /" writeback_value [7:0] $end
$var wire 1 0" zero $end
$var wire 1 1" zerofourc $end
$var wire 1 2" zpg_absolute $end
$var wire 1 3" zpg_indexed_x $end
$var wire 1 4" zpg_indexed_y $end
$var reg 16 5" addresscache [15:0] $end
$var reg 16 6" cycles [15:0] $end
$var reg 8 7" inst [7:0] $end
$var reg 16 8" pc [15:0] $end
$var reg 8 9" res [7:0] $end
$var reg 8 :" sr [7:0] $end
$var reg 16 ;" state [15:0] $end
$var reg 1 <" status_v $end
$var reg 8 =" temp_low [7:0] $end
$var reg 1 >" verbose $end
$var reg 16 ?" waddr [15:0] $end
$var reg 1 @" write_enable $end
$upscope $end
$upscope $end
$enddefinitions $end
#0
$dumpvars
x@"
b0xxxxxxxx ?"
0>"
bx ="
0<"
b1010 ;"
b110000 :"
bx 9"
b0 8"
bx 7"
b0 6"
bx 5"
x4"
x3"
x2"
x1"
00"
bx /"
x."
bx -"
bx ,"
x+"
x*"
bx )"
x("
0'"
0&"
x%"
0$"
bx #"
bx ""
bx !"
b0xxxx ~
x}
bx |
0{
xz
xy
xx
xw
bx v
bx u
b0 t
xs
xr
0q
xp
xo
xn
xm
xl
1k
xj
xi
xh
xg
xf
xe
xd
xc
xb
xa
x`
x_
x^
x]
x\
x[
xZ
xY
xX
xW
xV
xU
xT
xS
xR
xQ
xP
xO
xN
xM
xL
xK
xJ
xI
xH
xG
xF
xE
xD
xC
xB
xA
x@
x?
x>
x=
x<
x;
x:
x9
x8
x7
x6
x5
x4
x3
x2
x1
x0
0/
0.
0-
1,
x+
bx *
x)
x(
x'
x&
x%
x$
1#
1"
0!
$end
#46560
0"
#93120
0#
1"
#139680
0"
#186240
1"
#232800
0"
#279360
1#
1"
#325920
0"
#372480
0#
1"
#419040
0"
#465600
1"
#512160
0"
#558720
1#
1"
#605280
0"
#651840
0#
1"
#698400
0"
#744960
1"
#791520
0"
#838080
1#
1"
#884640
0"
#931200
0#
1"
#977760
0"
#1024320
b1 t
bx0x0x00xxxxxxxxx ,"
x&"
b10101001 u
b10101001 !"
b1 6"
b0 ;"
1'"
b1 8"
1!
1"
#1070880
0"
#1117440
0!
1#
1"
#1164000
0"
#1210560
0#
1"
#1257120
0"
#1303680
1"
#1350240
0"
#1396800
1#
1"
#1443360
0"
#1489920
0#
1"
#1536480
0"
#1583040
1"
#1629600
0"
#1676160
1#
1"
#1722720
0"
#1769280
0#
1"
#1815840
0"
#1862400
1"
#1908960
0"
#1955520
1#
1"
#2002080
0"
#2048640
0#
1"
#2095200
0"
#2141760
b1100 ~
b0 v
1w
b1100000 ""
0%"
0."
0z
0+"
1P
0y
0R
0&
0Q
02"
0m
0$
1l
1}
00
01"
0+
0U
04
0J
03
0b
0D
0^
05
0Z
0S
0[
0c
0G
0K
01
0%
03"
b10 t
0'
0<
0:
0>
0?
06
07
0;
08
0E
0F
0@
0_
0B
0a
0C
0A
0`
0*"
0W
0Y
0V
0X
0d
04"
0o
0p
0("
0s
1r
12
09
0N
0&"
b0xxxxxxxx ,"
b10 6"
b10101001 7"
0=
0O
0\
0]
0e
0f
0g
0h
0i
0x
0j
0T
0H
0I
0L
0M
0n
b10 8"
b1 ;"
0'"
0@"
b1100000 u
b1100000 !"
1!
1"
#2188320
0"
#2234880
0!
1#
1"
#2281440
0"
#2328000
0#
1"
#2374560
0"
#2421120
1"
#2467680
0"
#2514240
1#
1"
#2560800
0"
#2607360
0#
1"
#2653920
0"
#2700480
1"
#2747040
0"
#2793600
1#
1"
#2840160
0"
#2886720
0#
1"
#2933280
0"
#2979840
1"
#3026400
0"
#3072960
1#
1"
#3119520
0"
#3166080
0#
1"
#3212640
0"
#3259200
b10000101 ""
1&"
0(
b1100000 *
b1100000 |
b10000101 u
b10000101 !"
b11 6"
b0 ;"
1'"
b11 t
b11 8"
1!
1"
#3305760
0"
#3352320
0!
1#
1"
#3398880
0"
#3445440
0#
1"
#3492000
0"
#3538560
1"
#3585120
0"
#3631680
1#
1"
#3678240
0"
#3724800
0#
1"
#3771360
0"
#3817920
1"
#3864480
0"
#3911040
1#
1"
#3957600
0"
#4004160
0#
1"
#4050720
0"
#4097280
1"
#4143840
0"
#4190400
1#
1"
#4236960
0"
#4283520
0#
1"
#4330080
0"
#4376640
b0xxxx ~
bx v
0w
b1100000 )"
0%"
b1010000 ,"
1+"
bx ""
b1100000 -"
0P
0l
12"
1}
1b
b100 t
0&"
b100 6"
b10000101 7"
b100 8"
b1 ;"
0'"
b110000 :"
b1010000 u
b1010000 !"
b10000101 *
b10000101 |
1!
1"
#4423200
0"
#4469760
0!
1#
1"
#4516320
0"
#4562880
0#
1"
#4609440
0"
#4656000
1"
#4702560
0"
#4749120
1#
1"
#4795680
0"
#4842240
0#
1"
#4888800
0"
#4935360
1"
#4981920
0"
#5028480
1#
1"
#5075040
0"
#5121600
0#
1"
#5168160
0"
#5214720
1"
#5261280
0"
#5307840
1#
1"
#5354400
0"
#5400960
0#
1"
#5447520
0"
#5494080
b11100110 ,"
0+"
x(
bx *
bx |
b11100110 u
b11100110 !"
b101 6"
b1100000 9"
b1010000 ?"
1@"
b110 ;"
b100 5"
1!
1"
#5540640
0"
#5587200
0!
1#
1"
#5633760
0"
#5680320
0#
1"
#5726880
0"
#5773440
1"
#5820000
0"
#5866560
1#
1"
#5913120
0"
#5959680
0#
1"
#6006240
0"
#6052800
1"
#6099360
0"
#6145920
1#
1"
#6192480
0"
#6239040
0#
1"
#6285600
0"
#6332160
1"
#6378720
0"
#6425280
1#
1"
#6471840
0"
#6518400
0#
1"
#6564960
0"
#6611520
b101 t
b110 6"
b0 ;"
1'"
b101 8"
0@"
1!
1"
#6658080
0"
#6704640
0!
1#
1"
#6751200
0"
#6797760
0#
1"
#6844320
0"
#6890880
1"
#6937440
0"
#6984000
1#
1"
#7030560
0"
#7077120
0#
1"
#7123680
0"
#7170240
1"
#7216800
0"
#7263360
1#
1"
#7309920
0"
#7356480
0#
1"
#7403040
0"
#7449600
1"
#7496160
0"
#7542720
1#
1"
#7589280
0"
#7635840
0#
1"
#7682400
0"
#7728960
bx ""
1."
b1010001 /"
bx #"
bx v
1%"
0w
b1100000 )"
b101 ~
0}
1K
b0 -"
10
0b
0^
b1010000 t
b1010000 ,"
0+"
b1010000 u
b1010000 !"
b111 6"
b11100110 7"
b110 8"
b1 ;"
0'"
1!
1"
#7775520
0"
