mem.v
/* instruction memory */

`timescale 1ps/1ps

module mem(input clk,
    // read ports
    input [7:0]raddr0, output [7:0]rdata0,
    // write port
    input writeEnable, input [7:0]writeAddress, input [7:0]writeData);

    reg [7:0]mem[1023:0];

    /* Simulation -- read initial content from file */
    initial begin
        $readmemh("mem.hex",mem);
    end

    /* memory address register */
    reg [7:0]in0 = 16'hxxxx;
    reg [7:0]in1 = 16'hxxxx;

    /* memory data register */
    reg [7:0]out0 = 16'hxxxx;
    reg [7:0]out1 = 16'hxxxx;

    assign rdata0 = out0;
    assign rdata1 = out1;

    always @(posedge clk) begin
        if (writeEnable) begin
            $display("#mem[%x] <= %x",writeAddress,writeData);
            mem[writeAddress] <= writeData;
        end
        in0 <= raddr0;
        out0 <= mem[in0];        
    end

endmodule

cpu.v
`timescale 1ps/1ps

// STATES //
`define INIT 10
`define F0 0
`define F1 1 
`define HLT 2
`define F2 3
`define HLT2 4
`define M0 5
`define WB 6

// STATUS REGISTER BITS//
`define NEGATIVE 7
`define OVERFLOW 6  // 5 is unused
`define BREAK    4
`define DECIMAL  3
`define INT      2
`define ZERO     1
`define CARRY    0

// HEX //
`define A 10
`define B 11
`define C 12
`define D 13
`define E 14
`define F 15

// REGISTERS //
`define AC 0
`define X 1
`define Y 2
`define SP 3

// OPS // 
`define ADD 0
`define SUB 1
`define AND 2
`define OR  3
`define XOR 4
`define INC 5
`define DEC 6
`define SHR 7
`define SHL 8
`define RTR 9
`define RTL 10
`define LD  12

// RAM access time ~70ns?
// NES version of 6502 doesn't use BCD 

module cpu(input clk);

    // set to 1 for print statments
    reg verbose = 0;
    reg status_v = 0;
    reg [15:0] cycles = 0;


    reg [7:0] registers[3:0];
    //              REGISTER UPDATE             //
    wire modify_ac = i_lda | i_adc | i_and | i_asl | i_eor | i_lsr | i_ora | 
                     i_rol | i_ror | i_sbc | i_txa | i_tya;
    wire modify_x = i_tax | i_inx | i_tsx | i_dex | i_ldx;
    wire modify_y = i_dey | i_iny | i_ldy | i_tay;
    wire modify_sp = i_txs;

    wire [1:0]modified_reg = modify_ac ? `AC :
                             modify_x  ? `X  :
                             modify_y  ? `Y  :
                             modify_sp ? `SP :
                             2'bxx;       

    wire is_done = immediate | implied | accumulator ? (state == `F1) : 
                   absolute  ? (state == `M0) :
                   zpg_absolute ? (state == `M0) :
                   0;

    wire ready = (modify_ac | modify_x | modify_y | modify_sp) & is_done;

    wire [4:0] op = i_adc ? `ADD :
                     i_sbc ? `SUB : 
                     i_and ? `AND :
                     i_ora ? `OR  : 
                     i_eor ? `XOR : 
                     (i_inx | i_iny | i_inc) ? `INC :
                     (i_dex | i_dey | i_dec) ? `DEC :
                     i_lsr ? `SHR :
                     i_asl ? `SHL :
                     i_ror ? `RTR :
                     i_rol ? `RTL :
                     (i_lda | i_ldx | i_ldy | i_tax | 
                     i_tay | i_tsx | i_txa | i_txs | 
                     i_tya) ? `LD : 4'bx;
/*
    wire [7:0] newvalue = i_lda ? operand : 
                          i_adc && immediate ? registers[0] + operand + carry:
                          i_tax ? registers[0] : 
                          i_inx ? registers[1] + 1 : 8'hxx;
*/

    wire [7:0] operand1 = i_adc | i_sbc | i_and | i_ora | i_eor | 
                         ((i_lsr | i_asl | i_ror | i_rol) & accumulator) 
                         | i_tax | i_tay ? registers[`AC] : 
                          i_inx | i_dex | i_txa | i_txs ? registers[`X] : 
                          i_iny | i_dey | i_tya ? registers[`Y] : 
                          i_tsx ? registers[`SP] : 
                          (i_lda | i_ldx | i_ldy) ? memOut : 8'hxx;

    wire [7:0] operand2 = i_adc | i_sbc | i_and | i_ora | i_eor ? memOut : 8'hxx;
                          

    wire [7:0] newvalue = (op == `ADD) ? operand1 + operand2 + carry : 
                          (op == `SUB) ? operand1 - operand2 - carry :
                          (op == `AND) ? operand1 & operand2 :
                          (op == `OR)  ? operand1 | operand2 : 
                          (op == `XOR) ? operand1 ^ operand2 : 
                          (op == `INC) ? operand1 + 1 : 
                          (op == `DEC) ? operand1 - 1 :
                          (op == `SHR) ? operand1 >> 1 : 
                          (op == `SHL) ? operand1 << 1 :
                          (op == `RTR) ? (operand1 >> 1) & (carry << 7 | 8'h7F) :
                          (op == `RTL) ? (operand1 << 1) | (carry):
                          (op == `LD)  ? operand1 : 
                          8'hxx;

    reg [7:0] temp_low = 8'hx;

    // need to test overflow cases
    wire carrybit = (op == `ADD) ? 
                    ((operand1[7] == 1) && (operand2[7] == 1)) ||
                    ((operand1[7] != operand2[7]) && (newvalue[7] == 0)): 
                    (op == `SUB) ? (newvalue <= 0) : 0; // FIX THIS 

    wire overflowbit = i_adc && immediate ? 
                    ((registers[0][7] == 1) && (operand[7] == 1) && (newvalue[7] != 1) ||
                     (registers[0][7] == 0) && (operand[7] == 0) && (newvalue[7] != 0)) : 0; 

    always @(posedge clk) begin
        // only change one register at a time 
        if (ready) begin
            if (carrybit)begin
                if (verbose)
                    $display("carrying!");
                sr[`CARRY] <= 1;
            end
            if (overflowbit)begin
                if (verbose)
                    $display("overflowed!");
                sr[`OVERFLOW] <= 1;
            end
            if (newvalue[7] == 1)
                sr[`NEGATIVE] <= 1;
            else
                sr[`NEGATIVE] <= 0;
            if (newvalue == 0)
                sr[`ZERO] <= 1;
            else 
                sr[`ZERO] <= 0;
            if (i_rol | i_asl) begin
                sr[`CARRY] <= operand1[7];
            end
            if (i_ror | i_lsr)begin
                sr[`CARRY] <= operand1[0];
             end
            
            registers[modified_reg] <= newvalue;
            $display("#regs[%d] <= %x", modified_reg, newvalue);
        end
    end

    wire reading = (absolute | zpg_absolute) && !i_sta && !i_stx && !i_sty;

    // fetch 
    wire [7:0]memOut;
    wire [15:0]memIn = absolute & reading & (state == `F2) ? {memOut, temp_low} :
                       zpg_absolute & reading & (state == `F1) ? {8'h00, memOut} : 
                      {8'h00, pc}; 

    wire wen = zpg_absolute && !reading ? (state == `F1) : 
               writeback ? (state == `M0) : write_enable;

    reg write_enable = 1'bx;
    wire [15:0] write_address = absolute ? {memOut , temp_low} : 
                                zpg_absolute & !writeback ? {8'h00, memOut} : 
                                writeback & (state == `M0) ? addresscache : waddr;
    wire [7:0] reswire = zpg_absolute & !writeback ? write_value : 
                         writeback & (state == `M0) ? writeback_value : res;
    reg [7:0]res = 8'bxx;
    reg [15:0]waddr = 8'bxx;

    mem i0(clk,memIn,memOut, wen, write_address, reswire);

    reg [15:0] state = `INIT;
    reg [7:0]inst = 8'hxx;
    reg [15:0] addresscache;

    // inst decoding // 
    wire isOdd = inst[7:4] % 2 == 1;
    wire isEven = inst[7:4] % 2 == 0;
    wire higher_half = inst[7:4] >= 8;
    
    // inst groups 
    wire oddops = low(inst, 1) || low(inst, 5) ||
                  low(inst, 9) || low(inst, `D);
    wire evenops = low(inst, 6) || (low(inst, 10) && !higher_half) || 
                   low(inst, 14);
    wire zerofourc = low(inst, 0) || low(inst, 4) ||
                     low(inst, `C);

    // insts are split into high and low nibbles
    function high;
    input [7:0] inst;
    input [3:0] code;
    high = inst[7:4] == code;
    endfunction

    function low;
    input [7:0] inst;
    input [3:0] code;
    low = inst[3:0] == code;
    endfunction

    // 0 low-nibble (!higher_half) 
    wire i_brk = inst == 0;
    wire i_jsr = inst == 8'h20;
    wire i_rti = inst == 8'h40;
    wire i_rts = inst == 8'h60;
   
    // branches 0 low-nibble (odd high-nibble)
    wire branch = ((inst[3:0] == 0) && isOdd) || i_jmp;
    wire i_bpl = branch && high(inst, 1);
    wire i_bmi = branch && high(inst, 3);
    wire i_bvc = branch && high(inst, 5);
    wire i_bvs = branch && high(inst, 7);
    wire i_bcc = branch && high(inst, 9);
    wire i_bcs = branch && high(inst, `B);
    wire i_bne = branch && high(inst, `D);
    wire i_beq = branch && high(inst, `F);
    wire i_bit = (inst == 8'h24) || (inst == 8'h2c);
    wire i_jmp = (inst == 8'h4c) || (inst == 8'h6c);

    // 0, 4, c low-nibble (zerofourc)
    wire i_cpx = zerofourc && high(inst, `E);
    wire i_cpy = zerofourc && high(inst, `C);
    wire i_ldy = zerofourc && !(inst == 8'hb0) && (high(inst, 10) || high(inst, 11));
    
    // 1, 5, 9, D low-nibble (oddops)
    wire i_ora = oddops && (high(inst, 0) || high(inst, 1));
    wire i_and = oddops && (high(inst, 2) || high(inst, 3));
    wire i_eor = oddops && (high(inst, 4) || high(inst, 5));
    wire i_adc = oddops && (high(inst, 6) || high(inst, 7));
    wire i_sta = oddops && (high(inst, 8) || high(inst, 9));
    wire i_lda = (oddops && (high(inst, `A) || high(inst, `B))) || (inst == 8'ha2);
    wire i_cmp = oddops && (high(inst, `C) || high(inst, `D));
    wire i_sbc = oddops && (high(inst, `E) || high(inst, `F));

    // 6, 10 (lower half high), 14 low-nibble (evenops)
    wire i_asl = evenops && (high(inst, 0) || high(inst, 1));
    wire i_rol = evenops && (high(inst, 2) || high(inst, 3));
    wire i_lsr = evenops && (high(inst, 4) || high(inst, 5));
    wire i_ror = evenops && (high(inst, 6) || high(inst, 7));
    wire i_stx = evenops && (high(inst, 8) || high(inst, 9));
    wire i_ldx = evenops && (high(inst, `A) || high(inst, `B));
    wire i_dec = evenops && (high(inst, `C) || high(inst, `D));
    wire i_inc = evenops && (high(inst, `E) || high(inst, `F));

    // flags 8 low-nibble & odd high-nibble (tya exception)
    wire flags = isOdd && low(inst, 8) && !i_tya;
    wire i_clc = flags && high(inst, 1);
    wire i_sec = flags && high(inst, 3);
    wire i_cli = flags && high(inst, 5);
    wire i_sei = flags && high(inst, 7);
    wire i_clv = flags && high(inst, 11);
    wire i_cld = flags && high(inst, 13);
    wire i_sed = flags && high(inst, 15);

    // stack 8 low-nibble & even high-nibble & !higher_half
    wire stack_inst = isEven && !higher_half && (inst[3:0] == 8);
    wire i_php = stack_inst && (inst[7:4] == 0);
    wire i_plp = stack_inst && (inst[7:4] == 2);
    wire i_pha = stack_inst && (inst[7:4] == 4);
    wire i_pla = stack_inst && (inst[7:4] == 6);

    // transfer (no pattern...?)
    wire i_tax = inst == 8'haa; 
    wire i_tay = inst == 8'ha8;
    wire i_tsx = inst == 8'hba;
    wire i_txa = inst == 8'h8a;
    wire i_txs = inst == 8'h9a;
    wire i_tya = inst == 8'h98; 

    // misc 
    wire i_sty = (inst == 8'h84) || (inst == 8'h94) || (inst == 8'h8c);
    wire i_nop = (inst == 8'hea);
    wire i_dex = inst == 8'hca;
    wire i_dey = inst == 8'h88;
    wire i_inx = inst == 8'he8;
    wire i_iny = inst == 8'hc8;

    // modes
    wire immediate = (inst == 8'ha2) || (low(inst, 9) && isEven) || (low(inst, 0) && higher_half && isEven);   // 1 operand
    wire absolute  = ((low(inst, `C) || low(inst, `D) || low(inst, `E)) && isEven) || (inst == 8'h20) && !indirect;   // requires 2 operands
    wire zpg_absolute = (low(inst, 4) || low(inst, 5) || low(inst, 6)) && isEven;   // requires 1 operand
    wire implied = (inst == 8'h40) || (inst == 8'h60) || (inst == 0) || low(inst, 8) || (low(inst, `A) && higher_half); // 0 operands
    wire accumulator = low(inst, `A) && !higher_half && isEven;   // 0 operands
    wire abs_indexed_x = (low(inst, `C) || low(inst, `D) || low(inst, `E)) && isOdd && !abs_indexed_y; // 2 operands
    wire abs_indexed_y = (inst == 8'hbe) || (low(inst, 9) && isOdd); // 2 operands
    wire zpg_indexed_x = (low(inst, 4) || low(inst, 5) || low(inst, 6)) && isOdd && !zpg_indexed_y; // 1 operand
    wire zpg_indexed_y = (low(inst, 6) && (high(inst, 9) || high(inst, `B))); // 1 operand
    wire indirect = inst == 8'h6c;      // 2 operands
    wire indirect_x = low(inst, 1) && isEven;    // 1 operand
    wire indirect_y = low(inst, 1) && isOdd;    // 1 operand
    wire relative = low(inst, 0) && isOdd;      // 1 operand

    reg newinst = 0;

    wire [7:0] write_value = i_sta ? registers[`AC] :
                             i_stx ? registers[`X]  :
                             i_sty ? registers[`Y]  : 
                             i_asl ? 0              :
                             i_dec ? 0              :
                             i_inc ? 0              :
                             i_lsr ? 0              :
                             i_rol ? 0              :
                             i_ror ? 0              :
                             8'hxx;

    // for debugging 
    //modePrinter mp(clk, immediate, absolute, zpg_absolute, implied, accumulator, abs_indexed_x, abs_indexed_y, zpg_indexed_x, zpg_indexed_y, indirect, indirect_x, indirect_y, relative, inst, newinst);

    //instprinter ip(clk, i_adc, i_and, i_asl, i_bcc, i_bcs, i_beq, i_bit, i_bmi, i_bne, i_bpl, i_brk, i_bvc, i_bvs, i_clc, i_cld, i_cli, i_clv, i_cmp, i_cpx, i_cpy, i_dec, i_dex, i_dey, i_eor, i_inc, i_inx, i_iny, i_jmp, i_jsr, i_lda, i_ldx, i_ldy, i_lsr, i_nop, i_ora, i_pha, i_php, i_pla, i_plp, i_rol, i_ror, i_rti, i_rts, i_sbc, i_sec, i_sed, i_sei, i_sta, i_stx, i_sty, i_tax, i_tay, i_tsx, i_txa, i_txs, i_tya, inst);

    // registers
    reg [15:0]pc = 0;
    reg [7:0] sr = 8'b00110000;

    wire writeback = i_asl | i_dec | i_inc | i_lsr | i_rol | i_ror;

    wire [7:0] writeback_value = i_asl ? (memOut << 1 ) :
                           i_dec ? (memOut - 1 )  : 
                           i_inc ? (memOut + 1 )  :
                           i_lsr ? (memOut >> 1 ) :
                           i_rol ? (memOut << 1) | (carry) : 
                           i_ror ? (memOut >> 1) & (carry << 7 | 8'h7F) : 8'hxx;
  

    /*
    reg [7:0] ac = 0;
    reg [7:0] x  = 0;
    reg [7:0] y  = 0;
    reg [7:0] sp = 0;
    */
    
    // status bits
    wire negative  = sr[7];
    wire overflow  = sr[6];
    wire ignored   = sr[5];
    wire break     = sr[4];
    wire decimal   = sr[3];
    wire interrupt = sr[2];
    wire zero      = sr[1];
    wire carry     = sr[0];

    wire [7:0]operand = memOut;
    
    wire crossed = 0; // if a page boundary is crossed

    // implied = 1 byte
    // absolute, absolute x, absolute y = 3 bytes 
    // else 2 bytes
    always @(posedge clk) begin
        case (state)
            `INIT: begin
                pc <= pc + 1;
                registers[0] = 0;
                registers[1] = 0;
                registers[2] = 0;
                registers[3] = 0;
                state <= `F0;
            end
            `F0: begin
                write_enable <= 0;
                if (verbose)
                    $display("F0 %x %x", memOut, inst);
                if (status_v)
                    $display("sr %b", sr);
                if (memOut == 0)
                    state <= `HLT;
                if (memOut === 8'hxx)
                    state <= `HLT;
                if (implied === 1'bx | !(implied | accumulator) )
                    state <= `F1;
                inst <= memOut;
                newinst <= 1;
                pc <= pc + 1;
            end
            `F1 : begin
                if (verbose)
                    $display("F1 %x %x", memOut, inst);
                if (memOut === 8'hxx)
                    state <= `HLT;

                if (immediate)
                    state <= `F0;
                if (!zpg_absolute) // || !reading)
                    pc <= pc + 1;
                if (absolute)begin
                    temp_low <= memOut;
                    if (!reading) 
                       write_enable <= 1;
                    state <= `F2;
                end
                if (zpg_absolute)begin 
                    addresscache <= memIn;
                    state <= `M0;
                end
                if (i_sta && absolute)
                    res <= registers[0];
                if (implied | accumulator)begin
                    inst <= memOut;
                end
            end
            `F2 : begin
               if (verbose)
                    $display("F2 %x %x", memOut, inst);
                if (memOut === 8'hxx)
                    state <= `HLT;
                if (crossed & !reading) begin
                    write_enable <= 1;
                end
                else begin
                    write_enable <= 0;
                    if (!reading)
                        state <= `F0;
                    else begin
                        addresscache <= {8'h00, memOut};
                        state <= `M0;
                    end
                end
                if (!absolute || !reading)
                    pc <= pc + 1;
            end
            `M0 : begin
                if (verbose)
                    $display("M0 %x %x", memOut, inst);
                if (memOut == 8'hxx)
                    state <= `HLT;
                else  
                    state <= `F0;
                if (writeback & i_rol)
                    sr[`CARRY] <= memOut[7];
                if (writeback & i_ror)
                    sr[`CARRY] <= memOut[0];
                if (writeback & writeback_value == 0)
                    sr[`ZERO] <= 1;
                else 
                    sr[`ZERO] <= 0;
                if (writeback & writeback_value[7] == 1)
                    sr[`NEGATIVE] <= 1;
                else
                    sr[`NEGATIVE] <= 0;
                pc <= pc + 1;
            end
          /*  `WB : begin
                if (verbose)
                    $display("WB %x %x", memOut, inst);
                pc <= pc + 1;
                state <= `F0;
            end */
            `HLT : begin
                state <= `HLT2;
            end
            `HLT2 : begin
                $finish;
            end
        endcase
        
        cycles <= cycles + 1;
    end

endmodule

clock_gen.v
/* clock */
`timescale 1ps/1ps


// NOTE: subject to change - how to synchronize PPU/CPU? 
// PPU = m_clock / 4  = 21.4773 MHz / 4  = 5.37 MHz
// CPU = m_clock / 12 = 21.4773 MHz / 12 = 1.79 MHz

module clock_gen (input m_clk, output ppu_clk, output cpu_clk);
    
    reg [3:0] cycle = 0;
    reg ppu = 1;
    reg cpu = 0;

    assign ppu_clk = ppu;
    assign cpu_clk = cpu;

    // cpu only runs 1/12 during the 12th cycle (cycle 11) 
    // ppu only runs 4/12 during cycles 0, 3, 6, 9
    always @(posedge m_clk) begin
        if (cycle == 10)begin
            cpu <= 1;
            ppu <= 0;
        end
        else if (cycle == 11 || cycle == 2 || cycle == 5 || cycle == 8) begin
            ppu <= 1;
            cpu <= 0;
        end
        else begin
            ppu <= 0;
            cpu <= 0;
        end
            
        if (cycle == 11)
            cycle <= 0;
        else
            cycle <= cycle + 1;
    end
endmodule

master_clock.v
/* clock */
`timescale 1ps/1ps

// 21.4773 MHz = 21477300 cycles / second
// 21477300 cycles / second = 1 cycle = 46.56 ns per cycle ( round ?? ) 
// 46.56 ns = 46560.7874 ps

module master_clock(output clk);
    reg theClock = 1;

    assign clk = theClock;
    
    always begin
        #46560;
        theClock = !theClock;
    end
endmodule

nes.v
`timescale 1ps/1ps


module main();


wire m_clk;
// Master clock is split into PPU clock and CPU clock 
master_clock c0(m_clk);

    initial begin
        $dumpfile("cpu.vcd");
        $dumpvars(1,main);
        $dumpvars(1,c);
    end

wire ppu_clk;
wire cpu_clk;
clock_gen c1(m_clk, ppu_clk, cpu_clk);

wire [15:0]address_bus_in;
wire [7:0] data_bus_in;
wire [15:0]address_bus_out;
wire [7:0] data_bus_out;
wire wen;

cpu c(cpu_clk);

endmodule

cpu.vcd
$date
	Tue May 12 10:58:34 2015
$end
$version
	Icarus Verilog
$end
$timescale
	1ps
$end
$scope module main $end
$var wire 1 ! cpu_clk $end
$var wire 1 " m_clk $end
$var wire 1 # ppu_clk $end
$upscope $end
$scope module main $end
$scope module c $end
$var wire 1 $ abs_indexed_x $end
$var wire 1 % abs_indexed_y $end
$var wire 1 & absolute $end
$var wire 1 ' accumulator $end
$var wire 1 ( branch $end
$var wire 1 ) break $end
$var wire 1 * carry $end
$var wire 1 + carrybit $end
$var wire 1 ! clk $end
$var wire 1 , crossed $end
$var wire 1 - decimal $end
$var wire 1 . evenops $end
$var wire 1 / flags $end
$var wire 1 0 higher_half $end
$var wire 1 1 i_adc $end
$var wire 1 2 i_and $end
$var wire 1 3 i_asl $end
$var wire 1 4 i_bcc $end
$var wire 1 5 i_bcs $end
$var wire 1 6 i_beq $end
$var wire 1 7 i_bit $end
$var wire 1 8 i_bmi $end
$var wire 1 9 i_bne $end
$var wire 1 : i_bpl $end
$var wire 1 ; i_brk $end
$var wire 1 < i_bvc $end
$var wire 1 = i_bvs $end
$var wire 1 > i_clc $end
$var wire 1 ? i_cld $end
$var wire 1 @ i_cli $end
$var wire 1 A i_clv $end
$var wire 1 B i_cmp $end
$var wire 1 C i_cpx $end
$var wire 1 D i_cpy $end
$var wire 1 E i_dec $end
$var wire 1 F i_dex $end
$var wire 1 G i_dey $end
$var wire 1 H i_eor $end
$var wire 1 I i_inc $end
$var wire 1 J i_inx $end
$var wire 1 K i_iny $end
$var wire 1 L i_jmp $end
$var wire 1 M i_jsr $end
$var wire 1 N i_lda $end
$var wire 1 O i_ldx $end
$var wire 1 P i_ldy $end
$var wire 1 Q i_lsr $end
$var wire 1 R i_nop $end
$var wire 1 S i_ora $end
$var wire 1 T i_pha $end
$var wire 1 U i_php $end
$var wire 1 V i_pla $end
$var wire 1 W i_plp $end
$var wire 1 X i_rol $end
$var wire 1 Y i_ror $end
$var wire 1 Z i_rti $end
$var wire 1 [ i_rts $end
$var wire 1 \ i_sbc $end
$var wire 1 ] i_sec $end
$var wire 1 ^ i_sed $end
$var wire 1 _ i_sei $end
$var wire 1 ` i_sta $end
$var wire 1 a i_stx $end
$var wire 1 b i_sty $end
$var wire 1 c i_tax $end
$var wire 1 d i_tay $end
$var wire 1 e i_tsx $end
$var wire 1 f i_txa $end
$var wire 1 g i_txs $end
$var wire 1 h i_tya $end
$var wire 1 i ignored $end
$var wire 1 j immediate $end
$var wire 1 k implied $end
$var wire 1 l indirect $end
$var wire 1 m indirect_x $end
$var wire 1 n indirect_y $end
$var wire 1 o interrupt $end
$var wire 1 p isEven $end
$var wire 1 q isOdd $end
$var wire 1 r is_done $end
$var wire 16 s memIn [15:0] $end
$var wire 8 t memOut [7:0] $end
$var wire 2 u modified_reg [1:0] $end
$var wire 1 v modify_ac $end
$var wire 1 w modify_sp $end
$var wire 1 x modify_x $end
$var wire 1 y modify_y $end
$var wire 1 z negative $end
$var wire 8 { newvalue [7:0] $end
$var wire 1 | oddops $end
$var wire 5 } op [4:0] $end
$var wire 8 ~ operand [7:0] $end
$var wire 8 !" operand1 [7:0] $end
$var wire 8 "" operand2 [7:0] $end
$var wire 1 #" overflow $end
$var wire 1 $" overflowbit $end
$var wire 1 %" reading $end
$var wire 1 &" ready $end
$var wire 1 '" relative $end
$var wire 8 (" reswire [7:0] $end
$var wire 1 )" stack_inst $end
$var wire 1 *" wen $end
$var wire 16 +" write_address [15:0] $end
$var wire 8 ," write_value [7:0] $end
$var wire 1 -" writeback $end
$var wire 8 ." writeback_value [7:0] $end
$var wire 1 /" zero $end
$var wire 1 0" zerofourc $end
$var wire 1 1" zpg_absolute $end
$var wire 1 2" zpg_indexed_x $end
$var wire 1 3" zpg_indexed_y $end
$var reg 16 4" addresscache [15:0] $end
$var reg 16 5" cycles [15:0] $end
$var reg 8 6" inst [7:0] $end
$var reg 1 7" newinst $end
$var reg 16 8" pc [15:0] $end
$var reg 8 9" res [7:0] $end
$var reg 8 :" sr [7:0] $end
$var reg 16 ;" state [15:0] $end
$var reg 1 <" status_v $end
$var reg 8 =" temp_low [7:0] $end
$var reg 1 >" verbose $end
$var reg 16 ?" waddr [15:0] $end
$var reg 1 @" write_enable $end
$upscope $end
$upscope $end
$enddefinitions $end
#0
$dumpvars
x@"
b0xxxxxxxx ?"
0>"
bx ="
0<"
b1010 ;"
b110000 :"
bx 9"
b0 8"
07"
bx 6"
b0 5"
bx 4"
x3"
x2"
x1"
x0"
0/"
bx ."
x-"
bx ,"
bx +"
x*"
x)"
bx ("
x'"
0&"
x%"
x$"
0#"
bx ""
bx !"
bx ~
b0xxxx }
x|
bx {
0z
xy
xx
xw
xv
bx u
bx t
b0 s
0r
xq
xp
0o
xn
xm
xl
xk
xj
1i
xh
xg
xf
xe
xd
xc
xb
xa
x`
x_
x^
x]
x\
x[
xZ
xY
xX
xW
xV
xU
xT
xS
xR
xQ
xP
xO
xN
xM
xL
xK
xJ
xI
xH
xG
xF
xE
xD
xC
xB
xA
x@
x?
x>
x=
x<
x;
x:
x9
x8
x7
x6
x5
x4
x3
x2
x1
x0
x/
x.
0-
0,
x+
0*
1)
x(
x'
x&
x%
x$
1#
1"
0!
$end
#46560
0"
#93120
0#
1"
#139680
0"
#186240
1"
#232800
0"
#279360
1#
1"
#325920
0"
#372480
0#
1"
#419040
0"
#465600
1"
#512160
0"
#558720
1#
1"
#605280
0"
#651840
0#
1"
#698400
0"
#744960
1"
#791520
0"
#838080
1#
1"
#884640
0"
#931200
0#
1"
#977760
0"
#1024320
0$"
b1 s
bx0x0x00xxxxxxxxx +"
b10101001 t
b10101001 ~
b1 5"
b0 ;"
b1 8"
1!
1"
#1070880
0"
#1117440
0!
1#
1"
#1164000
0"
#1210560
0#
1"
#1257120
0"
#1303680
1"
#1350240
0"
#1396800
1#
1"
#1443360
0"
#1489920
0#
1"
#1536480
0"
#1583040
1"
#1629600
0"
#1676160
1#
1"
#1722720
0"
#1769280
0#
1"
#1815840
0"
#1862400
1"
#1908960
0"
#1955520
1#
1"
#2002080
0"
#2048640
0#
1"
#2095200
0"
#2141760
b1100000 {
0+
b1100 }
b0 u
1v
b1100000 !"
0%"
0-"
0y
0*"
1N
0x
0P
0&
0O
01"
0k
b10 s
0$
1j
1|
0.
00"
0(
0S
02
0H
01
0`
0B
0\
03
0X
0Q
0Y
0a
0E
0I
0/
0%
02"
0'
0:
08
0<
0=
04
05
09
06
0C
0D
0>
0]
0@
0_
0A
0?
0^
0)"
0U
0W
0T
0V
0b
03"
0m
0n
0'"
1&"
0q
1p
10
07
0L
1r
b0xxxxxxxx +"
b10 5"
b10 8"
17"
b10101001 6"
0;
0M
0Z
0[
0c
0d
0e
0f
0g
0w
0h
0R
0F
0G
0J
0K
0l
b1 ;"
0@"
b1100000 t
b1100000 ~
1!
1"
#2188320
0"
#2234880
0!
1#
1"
#2281440
0"
#2328000
0#
1"
#2374560
0"
#2421120
1"
#2467680
0"
#2514240
1#
1"
#2560800
0"
#2607360
0#
1"
#2653920
0"
#2700480
1"
#2747040
0"
#2793600
1#
1"
#2840160
0"
#2886720
0#
1"
#2933280
0"
#2979840
1"
#3026400
0"
#3072960
1#
1"
#3119520
0"
#3166080
0#
1"
#3212640
0"
#3259200
b10000101 {
b10000101 !"
b11 s
0&"
0r
b10000101 t
b10000101 ~
b110000 :"
b11 5"
b11 8"
b0 ;"
1!
1"
#3305760
0"
#3352320
0!
1#
1"
#3398880
0"
#3445440
0#
1"
#3492000
0"
#3538560
1"
#3585120
0"
#3631680
1#
1"
#3678240
0"
#3724800
0#
1"
#3771360
0"
#3817920
1"
#3864480
0"
#3911040
1#
1"
#3957600
0"
#4004160
0#
1"
#4050720
0"
#4097280
1"
#4143840
0"
#4190400
1#
1"
#4236960
0"
#4283520
0#
1"
#4330080
0"
#4376640
x+
b0xxxx }
bx {
bx u
0v
b1100000 ("
0%"
b1010000 +"
1*"
bx !"
b1100000 ,"
0N
0j
11"
b100 s
1|
1`
0&"
0r
b100 5"
b100 8"
b10000101 6"
b1 ;"
b1010000 t
b1010000 ~
1!
1"
#4423200
0"
#4469760
0!
1#
1"
#4516320
0"
#4562880
0#
1"
#4609440
0"
#4656000
1"
#4702560
0"
#4749120
1#
1"
#4795680
0"
#4842240
0#
1"
#4888800
0"
#4935360
1"
#4981920
0"
#5028480
1#
1"
#5075040
0"
#5121600
0#
1"
#5168160
0"
#5214720
1"
#5261280
0"
#5307840
1#
1"
#5354400
0"
#5400960
0#
1"
#5447520
0"
#5494080
1r
b11100110 +"
0*"
b11100110 t
b11100110 ~
b101 5"
b101 ;"
b100 4"
1!
1"
#5540640
0"
#5587200
0!
1#
1"
#5633760
0"
#5680320
0#
1"
#5726880
0"
#5773440
1"
#5820000
0"
#5866560
1#
1"
#5913120
0"
#5959680
0#
1"
#6006240
0"
#6052800
1"
#6099360
0"
#6145920
1#
1"
#6192480
0"
#6239040
0#
1"
#6285600
0"
#6332160
1"
#6378720
0"
#6425280
1#
1"
#6471840
0"
#6518400
0#
1"
#6564960
0"
#6611520
b101 s
0r
b110 5"
b101 8"
b110000 :"
b0 ;"
1!
1"
#6658080
0"
#6704640
0!
1#
1"
#6751200
0"
#6797760
0#
1"
#6844320
0"
#6890880
1"
#6937440
0"
#6984000
1#
1"
#7030560
0"
#7077120
0#
1"
#7123680
0"
#7170240
1"
#7216800
0"
#7263360
1#
1"
#7309920
0"
#7356480
0#
1"
#7403040
0"
#7449600
1"
#7496160
0"
#7542720
1#
1"
#7589280
0"
#7635840
0#
1"
#7682400
0"
#7728960
bx {
0+
bx !"
1-"
b1010001 ."
bx ""
bx u
1%"
0v
bx ("
b101 }
0|
1I
b0 ,"
b1010000 s
1.
0`
0\
b0xxxxxxxx +"
0*"
b1010000 t
b1010000 ~
b111 5"
b110 8"
b11100110 6"
b1 ;"
1!
1"
#7775520
0"
#7822080
0!
1#
1"
#7868640
0"
#7915200
0#
1"
#7961760
0"
#8008320
1"
#8054880
0"
#8101440
1#
1"
#8148000
0"
#8194560
0#
1"
#8241120
0"
#8287680
1"
#8334240
0"
#8380800
1#
1"
#8427360
0"
#8473920
0#
1"
#8520480
0"
#8567040
1"
#8613600
0"
#8660160
1#
1"
#8706720
0"
#8753280
0#
1"
#8799840
0"
#8846400
b1010000 +"
b1100001 ."
1r
b1100001 ("
b110 s
1*"
b1000 5"
b101 ;"
b1010000 4"
b1100000 t
b1100000 ~
1!
1"
#8892960
0"
#8939520
0!
1#
1"
#8986080
0"
#9032640
0#
1"
#9079200
0"
#9125760
1"
#9172320
0"
#9218880
1#
1"
#9265440
0"
#9312000
0#
1"
#9358560
0"
#9405120
1"
#9451680
0"
#9498240
1#
1"
#9544800
0"
#9591360
0#
1"
#9637920
0"
#9684480
1"
#9731040
0"
#9777600
1#
1"
#9824160
0"
#9870720
0#
1"
#9917280
0"
#9963840
b10100111 ."
b0xxxxxxxx +"
b111 s
0r
bx ("
0*"
b10100110 t
b10100110 ~
b1001 5"
b111 8"
b110000 :"
b0 ;"
1!
1"
#10010400
0"
#10056960
0!
1#
1"
#10103520
0"
#10150080
0#
1"
#10196640
0"
#10243200
1"
#10289760
0"
#10336320
1#
1"
#10382880
0"
#10429440
0#
1"
#10476000
0"
#10522560
1"
#10569120
0"
#10615680
1#
1"
#10662240
0"
#10708800
0#
1"
#10755360
0"
#10801920
1"
#10848480
0"
#10895040
1#
1"
#10941600
0"
#10988160
0#
1"
#11034720
0"
#11081280
b1010000 {
0+
b1010000 !"
b1010000 +"
b1100 }
bx ,"
0-"
b1 u
1x
bx ."
b1010000 s
1O
0I
b1010 5"
b1000 8"
b10100110 6"
b1 ;"
b1010000 t
b1010000 ~
1!
1"
#11127840
0"
#11174400
0!
1#
1"
